segmentation_pipeline/__init__.py
segmentation_pipeline/analize.py
segmentation_pipeline/predict.py
segmentation_pipeline/segmentation.py
segmentation_pipeline/__pycache__/__init__.cpython-36.pyc
segmentation_pipeline/__pycache__/segmentation.cpython-36.pyc
segmentation_pipeline/impl/__init__.py
segmentation_pipeline/impl/datasets.py
segmentation_pipeline/impl/rle.py
segmentation_pipeline/impl/deeplab/__init__.py
segmentation_pipeline/impl/deeplab/extract_weigths.py
segmentation_pipeline/impl/deeplab/load_weights.py
segmentation_pipeline/impl/deeplab/model.py
segmentation_pipeline/schemas/augmenters.raml
segmentation_pipeline/schemas/callbacks.raml
segmentation_pipeline/schemas/classification.raml
segmentation_pipeline/schemas/meta.raml
segmentation_pipeline/schemas/segmentation.raml
segmentation_pipeline-0.432.dist-info/LICENSE.txt
segmentation_pipeline-0.432.dist-info/METADATA
segmentation_pipeline-0.432.dist-info/WHEEL
segmentation_pipeline-0.432.dist-info/top_level.txt
segmentation_pipeline-0.432.dist-info/RECORD
