Metadata-Version: 2.1
Name: segmentation-pipeline
Version: 0.432
Summary: Segmentation support piepeline for Musket ML
Home-page: https://github.com/musket-ml/segmentation_training_pipeline
Author: Petrochenko Pavel
Author-email: petrochenko.pavel.a@gmail.com
License: MIT
Platform: UNKNOWN
Requires-Dist: musket-core
